edc_model_wrapper/__init__.py
edc_model_wrapper/apps.py
edc_model_wrapper/models.py
edc_model_wrapper/permissions_model_wrapper_mixin.py
edc_model_wrapper/stubs.py
edc_model_wrapper/parsers/__init__.py
edc_model_wrapper/parsers/keywords.py
edc_model_wrapper/parsers/next_url_parser.py
edc_model_wrapper/tests/__init__.py
edc_model_wrapper/tests/admin.py
edc_model_wrapper/tests/model_wrapper_test_helper.py
edc_model_wrapper/tests/models.py
edc_model_wrapper/tests/urls.py
edc_model_wrapper/tests/etc/user-aes-local.key
edc_model_wrapper/tests/etc/user-aes-restricted.key
edc_model_wrapper/tests/etc/user-rsa-local-private.pem
edc_model_wrapper/tests/etc/user-rsa-local-public.pem
edc_model_wrapper/tests/etc/user-rsa-restricted-private.pem
edc_model_wrapper/tests/etc/user-rsa-restricted-public.pem
edc_model_wrapper/tests/etc/user-salt-local.key
edc_model_wrapper/tests/etc/user-salt-restricted.key
edc_model_wrapper/tests/tests/__init__.py
edc_model_wrapper/tests/tests/test_example_wrappers.py
edc_model_wrapper/tests/tests/test_example_wrappers2.py
edc_model_wrapper/tests/tests/test_fields.py
edc_model_wrapper/tests/tests/test_keywords.py
edc_model_wrapper/tests/tests/test_model_wrapper.py
edc_model_wrapper/tests/tests/test_next_url.py
edc_model_wrapper/wrappers/__init__.py
edc_model_wrapper/wrappers/fields.py
edc_model_wrapper/wrappers/model_wrapper.py
edc_model_wrapper-0.3.13.dist-info/AUTHORS
edc_model_wrapper-0.3.13.dist-info/LICENSE
edc_model_wrapper-0.3.13.dist-info/METADATA
edc_model_wrapper-0.3.13.dist-info/WHEEL
edc_model_wrapper-0.3.13.dist-info/top_level.txt
edc_model_wrapper-0.3.13.dist-info/RECORD
